RTL/ALU.sv
module ALU (
    input wire [3:0] Opو
    input wire [31:0] InA,
    input wire [31:0] InB,
    output reg [31:0] Result,
    output reg Compare
);
  `include "../Definitions/alu_definitions.vh"

  always @(*) begin
    Result  = 32'b0;
    Compare = 1'b0;
    case (Op)
      ADD:  Result = InA + InB;
      SUB:  Result = InA - InB;
      AND:  Result = InA & InB;
      OR:   Result = InA | InB;
      XOR:  Result = InA ^ InB;
      SLL:  Result = InA << InB;
      SRL:  Result = InA >> InB;
      SRA:  Result = $signed(InA) >>> InB;
      SLT:  Compare = $signed(InA) < $signed(InB);
      SLTU: Compare = InA < InB;
      EQ:   Compare = InA == InB;
      NE:   Compare = InA != InB;
      LT:   Compare = $signed(InA) < $signed(InB);
      LTU:  Compare = InA < InB;
      GE:   Compare = $signed(InA) >= $signed(InB);
      GEU:  Compare = InA >= InB;
    endcase
  end

endmodule

Tests/ALU_tb.sv
`timescale 1ns / 1ps
`include "../RTL/ALU.sv"
module ALU_tb;

// Inputs
reg [31:0] inputA;
reg [31:0] inputB;
reg [3:0] Op;

// Outputs
wire [31:0] Result;
wire Compare;

// Instantiate the ALU
ALU uut (
    .InA(inputA), 
    .InB(inputB), 
    .Op(Op), 
    .Result(Result),
    .Compare(Compare)
);

initial begin
    $dumpfile("vcd/ALU.vcd");
    $dumpvars(0, ALU_tb);
    
    // Initialize Inputs
    inputA = 0079468;
    inputB = 0;
    Op = 0;

    // Wait 100 ns for global reset to finish
    #10;
    
    // Add test
    inputA = 32'd15;
    inputB = 32'd10;
    Op = 4'b0000; // ADD operation
    #10; // Wait for operation to complete
    
    // Subtract test
    inputA = 32'd25;
    inputB = 32'd10;
    Op = 4'b0001; // SUB operation
    #10; // Wait for operation to complete

    // AND test
    inputA = 32'hA;
    inputB = 32'h3;
    Op = 4'b0010; // AND operation
    #10; // Wait for operation to complete

    // OR test
    inputA = 32'hA;
    inputB = 32'h5;
    Op = 4'b0011; // OR operation
    #10; // Wait for operation to complete

    // XOR test
    inputA = 32'hF;
    inputB = 32'hF;
    Op = 4'b0100; // XOR operation
    #10; // Wait for operation to complete

    // Set less than (signed) test
    inputA = -5;
    inputB = 10;
    Op = 4'b0101; // SLT operation
    #10; // Wait for operation to complete

    // Set less than (unsigned) test
    inputA = 32'd5;
    inputB = 32'd10;
    Op = 4'b0110; // SLTU operation
    #10; // Wait for operation to complete
    
    // Complete the tests
    $display("Test complete");
end

endmodule

Tests/vcd/ALU.vcd
$date
	Tue Jan 09 18:29:16 2024
$end
$version
	Icarus Verilog
$end
$timescale
	1ps
$end
$scope module ALU_tb $end
$var wire 32 ! Result [31:0] $end
$var wire 1 " Compare $end
$var reg 4 # Op [3:0] $end
$var reg 32 $ inputA [31:0] $end
$var reg 32 % inputB [31:0] $end
$scope module uut $end
$var wire 32 & InA [31:0] $end
$var wire 32 ' InB [31:0] $end
$var wire 4 ( Op [3:0] $end
$var parameter 4 ) ADD $end
$var parameter 4 * AND $end
$var parameter 4 + EQ $end
$var parameter 4 , GE $end
$var parameter 4 - GEU $end
$var parameter 4 . LT $end
$var parameter 4 / LTU $end
$var parameter 4 0 NE $end
$var parameter 4 1 OR $end
$var parameter 4 2 SLL $end
$var parameter 4 3 SLT $end
$var parameter 4 4 SLTU $end
$var parameter 4 5 SRA $end
$var parameter 4 6 SRL $end
$var parameter 4 7 SUB $end
$var parameter 4 8 XOR $end
$var reg 1 " Compare $end
$var reg 32 9 Result [31:0] $end
$upscope $end
$upscope $end
$enddefinitions $end
$comment Show the parameter values. $end
$dumpall
b101 8
b1 7
b11 6
b100 5
b1001 4
b1000 3
b10 2
b111 1
b1011 0
b1110 /
b1100 .
b1111 -
b1101 ,
b1010 +
b110 *
b0 )
$end
#0
$dumpvars
b10011011001101100 9
b0 (
b0 '
b10011011001101100 &
b0 %
b10011011001101100 $
b0 #
0"
b10011011001101100 !
$end
#10000
b11001 !
b11001 9
b1010 %
b1010 '
b1111 $
b1111 &
#20000
b1111 !
b1111 9
b1 #
b1 (
b11001 $
b11001 &
#30000
b1010000 !
b1010000 9
b10 #
b10 (
b11 %
b11 '
b1010 $
b1010 &
#40000
b0 !
b0 9
b11 #
b11 (
b101 %
b101 '
#50000
b100 #
b100 (
b1111 %
b1111 '
b1111 $
b1111 &
#60000
b11111111111111111111111111110001 !
b11111111111111111111111111110001 9
b101 #
b101 (
b1010 %
b1010 '
b11111111111111111111111111111011 $
b11111111111111111111111111111011 &
#70000
b0 !
b0 9
b110 #
b110 (
b101 $
b101 &
